ggrecomb/__init__.py
ggrecomb/energy_functions.py
ggrecomb/library.py
ggrecomb/old_ggsr.py
ggrecomb/parent_alignment.py
ggrecomb/pdb_structure.py
ggrecomb/raspp.py
ggrecomb/step1.py
ggrecomb/step2.py
ggrecomb/step3.py
ggrecomb/step4.py
ggrecomb/tools/__init__.py
ggrecomb/tools/general_tools.py
ggrecomb/tools/pd_normalized_ligation_counts_18h_37C.p
ggrecomb/tools/step1_tools.py
ggrecomb/tools/step2_tools.py
ggrecomb/tools/step4_tools.py
ggrecomb-0.0.3.dist-info/LICENSE
ggrecomb-0.0.3.dist-info/WHEEL
ggrecomb-0.0.3.dist-info/METADATA
ggrecomb-0.0.3.dist-info/RECORD
