Metadata-Version: 2.1
Name: ggrecomb
Version: 0.0.3
Summary: Design recombinant protein libraries for Golden Gate Assembly.
Author: Bennett Bremer
Author-email: bennettjamesbremer@gmail.com
Requires-Python: >=3.9.1,<3.10.0
Classifier: Programming Language :: Python :: 3
Requires-Dist: biopython (>=1.79,<2.0)
Requires-Dist: scipy (>=1.6.3,<2.0.0)
Project-URL: Download, https://pypi.org/project/ggrecomb
Project-URL: Documentation, https://ggrecomb.readthedocs.io/en/latest
Project-URL: Source Code, https://github.com/RomeroLab/ggrecomb
